setup.py
kst2/__init__.py
kst2/admin.py
kst2/apps.py
kst2/fields.py
kst2/forms.py
kst2/models.py
kst2/states.py
kst2/tests.py
kst2/views.py
kst2/migrations/__init__.py
vaishali_indian_states_0325/__init__.py
vaishali_indian_states_0325/asgi.py
vaishali_indian_states_0325/settings.py
vaishali_indian_states_0325/urls.py
vaishali_indian_states_0325/wsgi.py
vaishali_indian_states_0325.egg-info/PKG-INFO
vaishali_indian_states_0325.egg-info/SOURCES.txt
vaishali_indian_states_0325.egg-info/dependency_links.txt
vaishali_indian_states_0325.egg-info/requires.txt
vaishali_indian_states_0325.egg-info/top_level.txt